djangooidc/__init__.py
djangooidc/backends.py
djangooidc/exceptions.py
djangooidc/oidc.py
djangooidc/urls.py
djangooidc/views.py
djangooidc/tests/__init__.py
djangooidc/tests/common.py
djangooidc/tests/test_settings.py
djangooidc/tests/test_views.py
django_logingov_backend-0.0.3.dist-info/LICENSE
django_logingov_backend-0.0.3.dist-info/METADATA
django_logingov_backend-0.0.3.dist-info/WHEEL
django_logingov_backend-0.0.3.dist-info/top_level.txt
django_logingov_backend-0.0.3.dist-info/RECORD
