Metadata-Version: 2.1
Name: django-logingov-backend
Version: 0.0.3
Summary: A small example package
Author-email: Example Author <author@example.com>
Classifier: Programming Language :: Python :: 3
Classifier: License :: OSI Approved :: MIT License
Classifier: Operating System :: OS Independent
Requires-Python: >=3.7
License-File: LICENSE
